clopure/__init__.py
clopure/basics.py
clopure/core.py
clopure/exceptions.py
clopure/extras.py
clopure/parser.py
clopure-0.1.3.data/scripts/clopure
clopure-0.1.3.dist-info/DESCRIPTION.rst
clopure-0.1.3.dist-info/METADATA
clopure-0.1.3.dist-info/RECORD
clopure-0.1.3.dist-info/WHEEL
clopure-0.1.3.dist-info/metadata.json
clopure-0.1.3.dist-info/top_level.txt
